{
  "slug": "igloukalyvanie-obman-ili-realnoe-spasenie-lichnyj-opyt-i-razbor-mifov",
  "title": "Иглоукалывание: обман или реальное спасение? Личный опыт и разбор мифов",
  "date": "2025-02-28",
  "cover": "/blog/igloukalyvanie-obman-ili-realnoe-spasenie-lichnyj-opyt-i-razbor-mifov/cover.jpg",
  "excerpt": "[ ](/articlinic) [Арти Клиник](/articlinic) 16 подписчиков Подписаться  Иглоукалывание: обман или реальное спасение? Личный опыт и разбор мифов 28 февраля28 фев 21 2 мин ![](/blog/…",
  "tags": [
    "arti-clinic",
    "dzen"
  ],
  "source": "https://dzen.ru/a/Z7muKqd1x0Hz08QN",
  "content": "[\n\n](/articlinic)\n\n[Арти Клиник](/articlinic)\n\n16 подписчиков\n\nПодписаться\n\n# Иглоукалывание: обман или реальное спасение? Личный опыт и разбор мифов\n\n28 февраля28 фев\n\n21\n\n2 мин\n\n![](/blog/igloukalyvanie-obman-ili-realnoe-spasenie-lichnyj-opyt-i-razbor-mifov/img-0.jpg)\n\n_Вы боитесь иголок?_ А зря — вот почему**Иглоукалывание** — одна из тех медицинских практик, которые вызывают горячие споры. Кто-то называет её панацеей, кто-то считает шарлатанством. Одни пациенты уверяют, что после сеансов боль уходит навсегда, другие скептически пожимают плечами.\n\nВ этой статье расскажем о своём опыте рефлексотерапии и разберем основные мифы, которые её окружают.  \n  \n**Что такое иглоукалывание на самом деле?**  \n  \nИглоукалывание (_или акупунктура_) — это метод традиционной китайской медицины, при котором в биологически активные точки тела вводятся тонкие иглы. Считается, что таким образом активируются внутренние ресурсы организма, улучшается кровообращение и снимается мышечное напряжение.  \n  \n**Мифы и правда об иглоукалывании:**  \n  \n**Миф 1. Это больно**  \nНа самом деле иглы для рефлексотерапии настолько тонкие, что их введение почти не ощущается. Иногда возникает лёгкое покалывание или тепло, но о боли речи не идёт.  \n  \n**Миф 2. Эффект только за счёт самовнушения**  \nСкептики утверждают, что иглоукалывание работает лишь на тех, кто верит в него. Однако научные исследования показывают, что воздействие на определённые точки действительно улучшает кровоток, снимает спазмы и запускает процессы восстановления тканей.  \n  \n**Миф 3. Это опасно**  \nПри соблюдении всех норм стерильности и правильной технике процедура абсолютно безопасна. Важно выбирать проверенные клиники и специалистов с медицинским образованием.  \n  \n**Миф 4. Эффект временный**  \nВ моём случае улучшение наступило после первого сеанса, но стойкий результат появился после курса процедур. Иглоукалывание помогло не только снять боль, но и устранить её причину.  \n\n**Для кого подходит иглоукалывание ?**  \n  \n\\- Людям с хроническими болями в спине, шее, суставах  \n\\- При головных болях и мигренях  \n\\- Для снятия мышечного напряжения и спазмов  \n\\- При стрессах и тревожных состояниях  \n\\- Для восстановления после травм  \n  \n**Личная история:**\n\n**Мария, 40 лет**\n\n_Как я решила попробовать иглоукалывание?_\n\n\"Несколько лет назад у меня начались регулярные боли в спине. Массажи, упражнения, мази — ничего не помогало. Обезболивающие действовали лишь на время. В какой-то момент знакомый посоветовал попробовать иглоукалывание. Честно скажу, сначала идея показалась странной: как крошечные иголки могут снять боль, если не справляются таблетки?\n\nНо от отчаяния я решила попробовать.\n\nИ знаете что? Уже после первого сеанса почувствовала облегчение.  \nПосле курса из 8 сеансов я практически забыла о боли в спине. Появилась лёгкость в движении, улучшился сон, снизился уровень стресса. **Теперь иглоукалывание для меня** — _это не странный метод из прошлого, а реальный способ помочь своему организму._  \n  \n**Стоит ли пробовать?**Если вы уже испробовали классические методы лечения и не получили результата — _однозначно да._\n\nНо важно подходить к выбору специалиста ответственно. Настоящий рефлексотерапевт не только знает точки воздействия, но и понимает физиологию организма.  \n  \nА вы пробовали иглоукалывание? Верите? Пишите в комментариях.\n\nПодпишитесь на канал,\n\nчтобы не пропустить новые публикации\n\nНе пропустите новые публикации\n\nПодписаться\n\n1\n\nРекомендуем почитать\n\n[](https://dzen.ru/a/aBsAY6NY2izAfqjC?from=feed&utm_referrer=https%3A%2F%2Fzen.yandex.com&integration=publishers_platform_yandex&place=article_related&secdata=CKzb14z4MiBrUI4JagQBayxsiAHjt4W1sJu72SKQAQA%3D&clid=560&rid=507916739.1886.1755420390175.45581&referrer_clid=228&)\n\n1 минута\n\n[\n\n](/id/617bbb979f046711a70e1bb6)\n\n[\n\nОксана Аверина - Секреты красоты, здоровья и энергии в 39 лет\n\n](/id/617bbb979f046711a70e1bb6)\n\n1254 читали · 3 месяца назад\n\nПодписаться\n\n[\n\n㊙️ Точка Вэй-чжун\n\n](https://dzen.ru/a/aBsAY6NY2izAfqjC?from=feed&utm_referrer=https%3A%2F%2Fzen.yandex.com&integration=publishers_platform_yandex&place=article_related&secdata=CKzb14z4MiBrUI4JagQBayxsiAHjt4W1sJu72SKQAQA%3D&clid=560&rid=507916739.1886.1755420390175.45581&referrer_clid=228& \"㊙️ Точка Вэй-чжун\")\n\nТочка вэй-чжун («изгиб, середина») расположена в середине изгиба, образующегося при сгибании колена, в центре подколенной складки. Используют и находят точку при согнутой в колене ноге, или когда пациент лежит на животе. Вэй-чжун массируется и натирается при лечении болезней мочевого пузыря (недержание мочи, затрудненное мочеиспускание), лечении болей в животе, рвотах, запорах, при поносе. Дополнительный эффект от воздействия на точку вэй-чжун: лечение геморроя; лечение болезней ножного канала мочевого...\n\n[](https://dzen.ru/a/Z-Ps2BgPeR1gI8pi?from=feed&utm_referrer=https%3A%2F%2Fzen.yandex.com&integration=publishers_platform_yandex&place=article_related&secdata=CNb1ntfgMiBrUI4JagQBayxsiAHjt4W1sJu72SKQAQA%3D&clid=560&rid=507916739.1886.1755420390175.45581&referrer_clid=228&)\n\n5 минут\n\n[\n\n](/id/63908cd4c222730d75c73e41)\n\n[\n\nНаркологическая клиника «Лордмед»\n\n](/id/63908cd4c222730d75c73e41)\n\n951 читали · 4 месяца назад\n\nПодписаться\n\n[\n\nИглоукалывание от курения: миф или реальный способ бросить?\n\n](https://dzen.ru/a/Z-Ps2BgPeR1gI8pi?from=feed&utm_referrer=https%3A%2F%2Fzen.yandex.com&integration=publishers_platform_yandex&place=article_related&secdata=CNb1ntfgMiBrUI4JagQBayxsiAHjt4W1sJu72SKQAQA%3D&clid=560&rid=507916739.1886.1755420390175.45581&referrer_clid=228& \"Иглоукалывание от курения: миф или реальный способ бросить?\")\n\nКурение — самый распространенный тип химической зависимости. По данным ВОЗ, в мире насчитывается порядка 1,3 миллиарда любителей табака. Бросить курить сложно. Некоторые переходят на жевательный табак или электронные сигареты, но это не менее вредно. Так появляется новая пагубная привычка. Если не получается избавиться от пристрастия самостоятельно, можно обратиться за помощью к специалистам. Сегодня наркологи практикуют разные способы лечения никотинозависимости. Более подробно об одном из них расскажут наши эксперты...\n\n[](https://dzen.ru/a/Z-4yqLcBaGKhmMSs?from=feed&utm_referrer=https%3A%2F%2Fzen.yandex.com&integration=publishers_platform_yandex&place=article_related&secdata=CJqc7tPfMiBrUI4JagQBayxsiAHjt4W1sJu72SKQAQA%3D&clid=560&rid=507916739.1886.1755420390175.45581&referrer_clid=228&)\n\n1 минута\n\n[\n\n](/id/5fd0a06246054b3e3157ab3b)\n\n[\n\nДоктор Ивашков: про онкологию и женское здоровье\n\n](/id/5fd0a06246054b3e3157ab3b)\n\n106 читали · 4 месяца назад\n\nПодписаться\n\n[\n\nИглоукалывание и акупунктура: есть ли доказанная польза\n\n](https://dzen.ru/a/Z-4yqLcBaGKhmMSs?from=feed&utm_referrer=https%3A%2F%2Fzen.yandex.com&integration=publishers_platform_yandex&place=article_related&secdata=CJqc7tPfMiBrUI4JagQBayxsiAHjt4W1sJu72SKQAQA%3D&clid=560&rid=507916739.1886.1755420390175.45581&referrer_clid=228& \"Иглоукалывание и акупунктура: есть ли доказанная польза\")\n\nИглоукалывание и акупунктура: есть ли доказанная польза? 🧐💉   Cегодня поговорим о методах, которые часто вызывают вопросы: иглоукалывание (акупунктура) и гирудотерапия (лечение пиявками). Эти практики используются веками, но что говорит современная наука?   Иглоукалывание: древность vs наука  Акупунктура — это введение тонких игл в определённые точки тела для улучшения здоровья.   Что говорит наука?   ✅ Эффективность при хронической боли: исследования показывают, что иглоукалывание может помочь при болях в спине, шее и остеоартрите...\n\nРеклама\n\nРеклама\n\nРеклама\n\n1\n"
}